pyxlimg/__init__.py
pyxlimg/xlimg.py
pyxlimg-0.1.5.dist-info/LICENSE
pyxlimg-0.1.5.dist-info/METADATA
pyxlimg-0.1.5.dist-info/WHEEL
pyxlimg-0.1.5.dist-info/RECORD
