Metadata-Version: 2.1
Name: pyxlimg
Version: 0.1.5
Summary: Image Extractor for XLSX files
Home-page: https://shortarrow.jp
License: MIT
Keywords: xlsx,image,PIL,Pillow,Excel
Author: ShortArrow
Author-email: bamboogeneral@shortarrow.jp
Maintainer: ShortArrow
Maintainer-email: bamboogeneral@shortarrow.jp
Requires-Python: >=3.10,<4.0
Classifier: License :: OSI Approved :: MIT License
Classifier: Programming Language :: Python :: 3
Classifier: Programming Language :: Python :: 3.10
Classifier: Programming Language :: Python :: 3.11
Classifier: Programming Language :: Python :: 3.12
Requires-Dist: Pillow (>=10.0,<11.0)
Project-URL: Documentation, https://pyxlimg.readthedocs.io/en/latest/pyxlimg.html
Project-URL: Repository, https://github.com/shortarrow/pyxlimg
